gtsam-stubs/__init__.pyi
gtsam-stubs/imuBias.pyi
gtsam-stubs/noiseModel.pyi
gtsam-stubs/symbol_shorthand.pyi
gtsam-stubs/utils.pyi
gtsam-stubs/gtsam/__init__.pyi
gtsam-stubs/gtsam/gtsfm.pyi
gtsam-stubs/gtsam/imuBias.pyi
gtsam-stubs/gtsam/lago.pyi
gtsam-stubs/gtsam/symbol_shorthand.pyi
gtsam-stubs/gtsam/utilities.pyi
gtsam-stubs/gtsam/utils.pyi
gtsam-stubs/gtsam/gtsam/__init__.pyi
gtsam-stubs/gtsam/gtsam/gtsfm.pyi
gtsam-stubs/gtsam/gtsam/imuBias.pyi
gtsam-stubs/gtsam/gtsam/lago.pyi
gtsam-stubs/gtsam/gtsam/symbol_shorthand.pyi
gtsam-stubs/gtsam/gtsam/utilities.pyi
gtsam-stubs/gtsam/gtsam/noiseModel/__init__.pyi
gtsam-stubs/gtsam/gtsam/noiseModel/mEstimator.pyi
gtsam-stubs/gtsam/noiseModel/__init__.pyi
gtsam-stubs/gtsam/noiseModel/mEstimator.pyi
gtsam-stubs/utils/__init__.pyi
gtsam-stubs/utils/circlePose3.pyi
gtsam-stubs/utils/logging_optimizer.pyi
gtsam-stubs/utils/plot.pyi
gtsam-stubs/utils/visual_data_generator.pyi
gtsam-stubs/utils/visual_isam.pyi
gtsam_stubs-4.2.dist-info/METADATA
gtsam_stubs-4.2.dist-info/WHEEL
gtsam_stubs-4.2.dist-info/top_level.txt
gtsam_stubs-4.2.dist-info/RECORD
