Metadata-Version: 2.1
Name: gtsam-stubs
Version: 4.2
Summary: PEP 561 type stubs for GTSAM
Home-page: http://www.gtsam.org
Maintainer: Fan Jiang
Maintainer-email: gtsam@example.com
License: BSD
Requires-Dist: gtsam >=4.2
Requires-Dist: typing-extensions >=3.7.4 ; python_version >= "3.8"
